tweetcaptureplus/__init__.py
tweetcaptureplus/cli.py
tweetcaptureplus/screenshot.py
tweetcaptureplus/examples/test_script.py
tweetcaptureplus/examples/tweet_screenshot.py
tweetcaptureplus/examples/tweet_screenshot_concurrent.py
tweetcaptureplus/tests/test_screenshot.py
tweetcaptureplus/utils/__init__.py
tweetcaptureplus/utils/utils.py
tweetcaptureplus/utils/webdriver.py
tweetcaptureplus-0.3.4.dist-info/licenses/LICENSE
tweetcaptureplus-0.3.4.dist-info/METADATA
tweetcaptureplus-0.3.4.dist-info/WHEEL
tweetcaptureplus-0.3.4.dist-info/entry_points.txt
tweetcaptureplus-0.3.4.dist-info/top_level.txt
tweetcaptureplus-0.3.4.dist-info/RECORD
