Metadata-Version: 2.4
Name: tweetcaptureplus
Version: 0.3.4
Summary: Easily take screenshots of tweets, mentions, and full threads.
Author-email: Abdallah Heidar <abdallahheidar@gmail.com>, Alperen Çetin <xacnio@pm.me>
License-Expression: MIT
Project-URL: Homepage, https://github.com/abdallahheidar/tweetcaptureplus
Project-URL: Issues, https://github.com/abdallahheidar/tweetcaptureplus/issues
Keywords: twitter,screenshot,capture,tweet,thread,mention
Classifier: Programming Language :: Python :: 3.9
Classifier: Programming Language :: Python :: 3.10
Classifier: Programming Language :: Python :: 3.11
Classifier: Programming Language :: Python :: 3.12
Classifier: Operating System :: OS Independent
Requires-Python: >=3.9
License-File: LICENSE
Requires-Dist: python-dotenv==1.2.1
Requires-Dist: selenium==4.38.0
Requires-Dist: pillow==12.0.0
Requires-Dist: webdriver-manager==4.0.2
Dynamic: license-file
Dynamic: requires-dist
